README.md
setup.cfg
setup.py
distributions/Binomialdistribution.py
distributions/Gaussiandistribution.py
distributions/Generaldistribution.py
distributions/__init__.py
wizarniak_distributions.egg-info/PKG-INFO
wizarniak_distributions.egg-info/SOURCES.txt
wizarniak_distributions.egg-info/dependency_links.txt
wizarniak_distributions.egg-info/not-zip-safe
wizarniak_distributions.egg-info/top_level.txt